{
  "resolvedId": "/home/marcio/Documentos/projetos/money-management/src/components/atoms/Textarea/index.tsx",
  "transforms": [
    {
      "name": "__load__",
      "result": "/* --- main --- */\nimport { LegacyRef, forwardRef } from \"react\";\n\n/* --- utils --- */\nimport { css } from \"@utils/css\";\n\n/* --- styles --- */\nimport { textAreaClass } from \"./styles\";\n\n/* --- types --- */\nimport { TextareaProps } from \"./types\";\n\nfunction TextareaComponent({ className = \"\", ...props }: TextareaProps, ref?: LegacyRef<HTMLTextAreaElement>) {\n    return <textarea className={css(textAreaClass, className)} rows={5} {...props} ref={ref}></textarea>;\n}\n\nexport const Textarea = forwardRef(TextareaComponent);\n",
      "start": 1733614384816,
      "end": 1733614384816
    },
    {
      "name": "vite:css",
      "start": 1733614384816,
      "end": 1733614384816,
      "order": "normal"
    },
    {
      "name": "vite:json",
      "start": 1733614384816,
      "end": 1733614384816,
      "order": "normal"
    },
    {
      "name": "vite:worker",
      "start": 1733614384816,
      "end": 1733614384816,
      "order": "normal"
    },
    {
      "name": "vite:react-swc",
      "result": "if (!window.$RefreshReg$) throw new Error(\"React refresh preamble was not loaded. Something is wrong.\");\nconst prevRefreshReg = window.$RefreshReg$;\nconst prevRefreshSig = window.$RefreshSig$;\nwindow.$RefreshReg$ = RefreshRuntime.getRefreshReg(\"/home/marcio/Documentos/projetos/money-management/src/components/atoms/Textarea/index.tsx\");\nwindow.$RefreshSig$ = RefreshRuntime.createSignatureFunctionForTransform;\n\nimport * as RefreshRuntime from \"/@react-refresh\";\n\n/* --- main --- */ import { jsxDEV as _jsxDEV } from \"react/jsx-dev-runtime\";\nimport { forwardRef } from \"react\";\n/* --- utils --- */ import { css } from \"@utils/css\";\n/* --- styles --- */ import { textAreaClass } from \"./styles\";\nfunction TextareaComponent({ className = \"\", ...props }, ref) {\n    return /*#__PURE__*/ _jsxDEV(\"textarea\", {\n        className: css(textAreaClass, className),\n        rows: 5,\n        ...props,\n        ref: ref\n    }, void 0, false, {\n        fileName: \"/home/marcio/Documentos/projetos/money-management/src/components/atoms/Textarea/index.tsx\",\n        lineNumber: 14,\n        columnNumber: 12\n    }, this);\n}\n_c = TextareaComponent;\nexport const Textarea = /*#__PURE__*/ forwardRef(TextareaComponent);\n_c1 = Textarea;\nvar _c, _c1;\n$RefreshReg$(_c, \"TextareaComponent\");\n$RefreshReg$(_c1, \"Textarea\");\n\n\nwindow.$RefreshReg$ = prevRefreshReg;\nwindow.$RefreshSig$ = prevRefreshSig;\n\nRefreshRuntime.__hmr_import(import.meta.url).then((currentExports) => {\n  RefreshRuntime.registerExportsForReactRefresh(\"/home/marcio/Documentos/projetos/money-management/src/components/atoms/Textarea/index.tsx\", currentExports);\n  import.meta.hot.accept((nextExports) => {\n    if (!nextExports) return;\n    const invalidateMessage = RefreshRuntime.validateRefreshBoundaryAndEnqueueUpdate(\"/home/marcio/Documentos/projetos/money-management/src/components/atoms/Textarea/index.tsx\", currentExports, nextExports);\n    if (invalidateMessage) import.meta.hot.invalidate(invalidateMessage);\n  });\n});\n",
      "start": 1733614384816,
      "end": 1733614384821,
      "order": "normal",
      "sourcemaps": {
        "version": 3,
        "sources": [
          "index.tsx"
        ],
        "sourcesContent": [
          "/* --- main --- */\nimport { LegacyRef, forwardRef } from \"react\";\n\n/* --- utils --- */\nimport { css } from \"@utils/css\";\n\n/* --- styles --- */\nimport { textAreaClass } from \"./styles\";\n\n/* --- types --- */\nimport { TextareaProps } from \"./types\";\n\nfunction TextareaComponent({ className = \"\", ...props }: TextareaProps, ref?: LegacyRef<HTMLTextAreaElement>) {\n    return <textarea className={css(textAreaClass, className)} rows={5} {...props} ref={ref}></textarea>;\n}\n\nexport const Textarea = forwardRef(TextareaComponent);\n"
        ],
        "names": [
          "forwardRef",
          "css",
          "textAreaClass",
          "TextareaComponent",
          "className",
          "props",
          "ref",
          "textarea",
          "rows",
          "Textarea"
        ],
        "mappings": ";;;;;;;;AAAA,gBAAgB;AAChB,SAAoBA,UAAU,QAAQ,QAAQ;AAE9C,iBAAiB,GACjB,SAASC,GAAG,QAAQ,aAAa;AAEjC,kBAAkB,GAClB,SAASC,aAAa,QAAQ,WAAW;AAKzC,SAASC,kBAAkB,EAAEC,YAAY,EAAE,EAAE,GAAGC,OAAsB,EAAEC,GAAoC;IACxG,qBAAO,QAACC;QAASH,WAAWH,IAAIC,eAAeE;QAAYI,MAAM;QAAI,GAAGH,KAAK;QAAEC,KAAKA;;;;;;AACxF;KAFSH;AAIT,OAAO,MAAMM,yBAAWT,WAAWG,mBAAmB"
      }
    },
    {
      "name": "vite:define",
      "start": 1733614384821,
      "end": 1733614384821,
      "order": "normal"
    },
    {
      "name": "vite:css-post",
      "start": 1733614384821,
      "end": 1733614384821,
      "order": "normal"
    },
    {
      "name": "vite:worker-import-meta-url",
      "start": 1733614384821,
      "end": 1733614384821,
      "order": "normal"
    },
    {
      "name": "vite:asset-import-meta-url",
      "start": 1733614384821,
      "end": 1733614384821,
      "order": "normal"
    },
    {
      "name": "vite:dynamic-import-vars",
      "start": 1733614384821,
      "end": 1733614384821,
      "order": "normal"
    },
    {
      "name": "vite:import-glob",
      "start": 1733614384821,
      "end": 1733614384821,
      "order": "normal"
    },
    {
      "name": "vite:client-inject",
      "start": 1733614384821,
      "end": 1733614384821,
      "order": "normal"
    },
    {
      "name": "vite:import-analysis",
      "result": "import { createHotContext as __vite__createHotContext } from \"/@vite/client\";import.meta.hot = __vite__createHotContext(\"/src/components/atoms/Textarea/index.tsx\");if (!window.$RefreshReg$) throw new Error(\"React refresh preamble was not loaded. Something is wrong.\");\nconst prevRefreshReg = window.$RefreshReg$;\nconst prevRefreshSig = window.$RefreshSig$;\nwindow.$RefreshReg$ = RefreshRuntime.getRefreshReg(\"/home/marcio/Documentos/projetos/money-management/src/components/atoms/Textarea/index.tsx\");\nwindow.$RefreshSig$ = RefreshRuntime.createSignatureFunctionForTransform;\n\nimport * as RefreshRuntime from \"/@react-refresh\";\n\n/* --- main --- */ import __vite__cjsImport1_react_jsxDevRuntime from \"/node_modules/.vite/deps/react_jsx-dev-runtime.js?v=c12ee5d5\"; const _jsxDEV = __vite__cjsImport1_react_jsxDevRuntime[\"jsxDEV\"];\nimport __vite__cjsImport2_react from \"/node_modules/.vite/deps/react.js?v=dcff9708\"; const forwardRef = __vite__cjsImport2_react[\"forwardRef\"];\n/* --- utils --- */ import { css } from \"/src/utils/css.ts\";\n/* --- styles --- */ import { textAreaClass } from \"/src/components/atoms/Textarea/styles.ts\";\nfunction TextareaComponent({ className = \"\", ...props }, ref) {\n    return /*#__PURE__*/ _jsxDEV(\"textarea\", {\n        className: css(textAreaClass, className),\n        rows: 5,\n        ...props,\n        ref: ref\n    }, void 0, false, {\n        fileName: \"/home/marcio/Documentos/projetos/money-management/src/components/atoms/Textarea/index.tsx\",\n        lineNumber: 14,\n        columnNumber: 12\n    }, this);\n}\n_c = TextareaComponent;\nexport const Textarea = /*#__PURE__*/ forwardRef(TextareaComponent);\n_c1 = Textarea;\nvar _c, _c1;\n$RefreshReg$(_c, \"TextareaComponent\");\n$RefreshReg$(_c1, \"Textarea\");\n\n\nwindow.$RefreshReg$ = prevRefreshReg;\nwindow.$RefreshSig$ = prevRefreshSig;\n\nRefreshRuntime.__hmr_import(import.meta.url).then((currentExports) => {\n  RefreshRuntime.registerExportsForReactRefresh(\"/home/marcio/Documentos/projetos/money-management/src/components/atoms/Textarea/index.tsx\", currentExports);\n  import.meta.hot.accept((nextExports) => {\n    if (!nextExports) return;\n    const invalidateMessage = RefreshRuntime.validateRefreshBoundaryAndEnqueueUpdate(\"/home/marcio/Documentos/projetos/money-management/src/components/atoms/Textarea/index.tsx\", currentExports, nextExports);\n    if (invalidateMessage) import.meta.hot.invalidate(invalidateMessage);\n  });\n});\n",
      "start": 1733614384821,
      "end": 1733614384822,
      "order": "normal",
      "sourcemaps": null
    }
  ]
}
